Workbook

Sheet Resumo
A1: Resumo do Acompanhamento
A2: Sprint | B2: Total tarefas | C2: Não iniciada | D2: Em andamento | E2: Bloqueada | F2: Em validação | G2: Concluída
A3: Sprint 0 | B3: =COUNTIF('Master Backlog'!$B:$B,A3) | C3: =COUNTIFS('Master Backlog'!$B:$B,$A3,'Master Backlog'!$G:$G,"Não iniciada") | D3: =COUNTIFS('Master Backlog'!$B:$B,$A3,'Master Backlog'!$G:$G,"Em andamento") | E3: =COUNTIFS('Master Backlog'!$B:$B,$A3,'Master Backlog'!$G:$G,"Bloqueada") | F3: =COUNTIFS('Master Backlog'!$B:$B,$A3,'Master Backlog'!$G:$G,"Em validação") | G3: =COUNTIFS('Master Backlog'!$B:$B,$A3,'Master Backlog'!$G:$G,"Concluída")
A4: Sprint 1 | B4: =COUNTIF('Master Backlog'!$B:$B,A4) | C4: =COUNTIFS('Master Backlog'!$B:$B,$A4,'Master Backlog'!$G:$G,"Não iniciada") | D4: =COUNTIFS('Master Backlog'!$B:$B,$A4,'Master Backlog'!$G:$G,"Em andamento") | E4: =COUNTIFS('Master Backlog'!$B:$B,$A4,'Master Backlog'!$G:$G,"Bloqueada") | F4: =COUNTIFS('Master Backlog'!$B:$B,$A4,'Master Backlog'!$G:$G,"Em validação") | G4: =COUNTIFS('Master Backlog'!$B:$B,$A4,'Master Backlog'!$G:$G,"Concluída")
A5: Sprint 2 | B5: =COUNTIF('Master Backlog'!$B:$B,A5) | C5: =COUNTIFS('Master Backlog'!$B:$B,$A5,'Master Backlog'!$G:$G,"Não iniciada") | D5: =COUNTIFS('Master Backlog'!$B:$B,$A5,'Master Backlog'!$G:$G,"Em andamento") | E5: =COUNTIFS('Master Backlog'!$B:$B,$A5,'Master Backlog'!$G:$G,"Bloqueada") | F5: =COUNTIFS('Master Backlog'!$B:$B,$A5,'Master Backlog'!$G:$G,"Em validação") | G5: =COUNTIFS('Master Backlog'!$B:$B,$A5,'Master Backlog'!$G:$G,"Concluída")
A6: Sprint 3 | B6: =COUNTIF('Master Backlog'!$B:$B,A6) | C6: =COUNTIFS('Master Backlog'!$B:$B,$A6,'Master Backlog'!$G:$G,"Não iniciada") | D6: =COUNTIFS('Master Backlog'!$B:$B,$A6,'Master Backlog'!$G:$G,"Em andamento") | E6: =COUNTIFS('Master Backlog'!$B:$B,$A6,'Master Backlog'!$G:$G,"Bloqueada") | F6: =COUNTIFS('Master Backlog'!$B:$B,$A6,'Master Backlog'!$G:$G,"Em validação") | G6: =COUNTIFS('Master Backlog'!$B:$B,$A6,'Master Backlog'!$G:$G,"Concluída")
A7: Sprint 4 | B7: =COUNTIF('Master Backlog'!$B:$B,A7) | C7: =COUNTIFS('Master Backlog'!$B:$B,$A7,'Master Backlog'!$G:$G,"Não iniciada") | D7: =COUNTIFS('Master Backlog'!$B:$B,$A7,'Master Backlog'!$G:$G,"Em andamento") | E7: =COUNTIFS('Master Backlog'!$B:$B,$A7,'Master Backlog'!$G:$G,"Bloqueada") | F7: =COUNTIFS('Master Backlog'!$B:$B,$A7,'Master Backlog'!$G:$G,"Em validação") | G7: =COUNTIFS('Master Backlog'!$B:$B,$A7,'Master Backlog'!$G:$G,"Concluída")
A8: Sprint 5 | B8: =COUNTIF('Master Backlog'!$B:$B,A8) | C8: =COUNTIFS('Master Backlog'!$B:$B,$A8,'Master Backlog'!$G:$G,"Não iniciada") | D8: =COUNTIFS('Master Backlog'!$B:$B,$A8,'Master Backlog'!$G:$G,"Em andamento") | E8: =COUNTIFS('Master Backlog'!$B:$B,$A8,'Master Backlog'!$G:$G,"Bloqueada") | F8: =COUNTIFS('Master Backlog'!$B:$B,$A8,'Master Backlog'!$G:$G,"Em validação") | G8: =COUNTIFS('Master Backlog'!$B:$B,$A8,'Master Backlog'!$G:$G,"Concluída")
A9: Sprint 6 | B9: =COUNTIF('Master Backlog'!$B:$B,A9) | C9: =COUNTIFS('Master Backlog'!$B:$B,$A9,'Master Backlog'!$G:$G,"Não iniciada") | D9: =COUNTIFS('Master Backlog'!$B:$B,$A9,'Master Backlog'!$G:$G,"Em andamento") | E9: =COUNTIFS('Master Backlog'!$B:$B,$A9,'Master Backlog'!$G:$G,"Bloqueada") | F9: =COUNTIFS('Master Backlog'!$B:$B,$A9,'Master Backlog'!$G:$G,"Em validação") | G9: =COUNTIFS('Master Backlog'!$B:$B,$A9,'Master Backlog'!$G:$G,"Concluída")
A10: Sprint 7 | B10: =COUNTIF('Master Backlog'!$B:$B,A10) | C10: =COUNTIFS('Master Backlog'!$B:$B,$A10,'Master Backlog'!$G:$G,"Não iniciada") | D10: =COUNTIFS('Master Backlog'!$B:$B,$A10,'Master Backlog'!$G:$G,"Em andamento") | E10: =COUNTIFS('Master Backlog'!$B:$B,$A10,'Master Backlog'!$G:$G,"Bloqueada") | F10: =COUNTIFS('Master Backlog'!$B:$B,$A10,'Master Backlog'!$G:$G,"Em validação") | G10: =COUNTIFS('Master Backlog'!$B:$B,$A10,'Master Backlog'!$G:$G,"Concluída")
A11: Sprint 8 | B11: =COUNTIF('Master Backlog'!$B:$B,A11) | C11: =COUNTIFS('Master Backlog'!$B:$B,$A11,'Master Backlog'!$G:$G,"Não iniciada") | D11: =COUNTIFS('Master Backlog'!$B:$B,$A11,'Master Backlog'!$G:$G,"Em andamento") | E11: =COUNTIFS('Master Backlog'!$B:$B,$A11,'Master Backlog'!$G:$G,"Bloqueada") | F11: =COUNTIFS('Master Backlog'!$B:$B,$A11,'Master Backlog'!$G:$G,"Em validação") | G11: =COUNTIFS('Master Backlog'!$B:$B,$A11,'Master Backlog'!$G:$G,"Concluída")
A12: Sprint 9 | B12: =COUNTIF('Master Backlog'!$B:$B,A12) | C12: =COUNTIFS('Master Backlog'!$B:$B,$A12,'Master Backlog'!$G:$G,"Não iniciada") | D12: =COUNTIFS('Master Backlog'!$B:$B,$A12,'Master Backlog'!$G:$G,"Em andamento") | E12: =COUNTIFS('Master Backlog'!$B:$B,$A12,'Master Backlog'!$G:$G,"Bloqueada") | F12: =COUNTIFS('Master Backlog'!$B:$B,$A12,'Master Backlog'!$G:$G,"Em validação") | G12: =COUNTIFS('Master Backlog'!$B:$B,$A12,'Master Backlog'!$G:$G,"Concluída")

Sheet Master Backlog
A1: ID | B1: Sprint | C1: Área | D1: Descrição | E1: Arquivos principais | F1: Dependências | G1: Status | H1: Critério de aceite | I1: Responsável principal | J1: Prioridade | K1: Data início | L1: Data conclusão | M1: Observações/Bloqueios
A2: OPS-001 | B2: 0 | C2: Operação | D2: Criar estrutura raiz do repositório | E2: .gitignore; .env.example; README.md; Makefile; diretórios base | F2: — | G2: Não iniciada | H2: Estrutura raiz criada e consistente com a arquitetura | I2: Arquiteto / DevOps | J2: Alta
A3: BE-001 | B3: 0 | C3: Backend | D3: Inicializar backend FastAPI | E3: backend/app/main.py; backend/app/api/; backend/app/core/; requirements/pyproject | F3: OPS-001 | G3: Não iniciada | H3: Backend sobe localmente | I3: Backend | J3: Alta
A4: BE-002 | B4: 0 | C4: Backend | D4: Implementar endpoint /health | E4: backend/app/api/routes/health.py; backend/app/main.py | F4: BE-001 | G4: Não iniciada | H4: GET /health responde 200 com payload mínimo | I4: Backend | J4: Alta
A5: FE-001 | B5: 0 | C5: Frontend | D5: Inicializar frontend Next.js com TypeScript | E5: frontend/package.json; tsconfig; src/app/layout.tsx; src/app/page.tsx | F5: OPS-001 | G5: Não iniciada | H5: Frontend sobe localmente | I5: Frontend | J5: Alta
A6: FE-002 | B6: 0 | C6: Frontend | D6: Criar cliente básico de API | E6: frontend/src/lib/api.ts; frontend/src/lib/constants.ts | F6: FE-001, BE-002 | G6: Não iniciada | H6: Frontend consegue chamar o backend | I6: Frontend | J6: Alta
A7: FE-003 | B7: 0 | C7: Frontend | D7: Criar página inicial técnica mínima | E7: frontend/src/app/page.tsx | F7: FE-002 | G7: Não iniciada | H7: Página inicial mostra status da API | I7: Frontend | J7: Média
A8: QA-001 | B8: 0 | C8: Testes | D8: Criar teste inicial do backend | E8: backend/tests/test_health.py | F8: BE-002 | G8: Não iniciada | H8: Teste cobre status 200 e contrato mínimo do /health | I8: QA / Backend | J8: Alta
A9: DOC-001 | B9: 0 | C9: Documentação | D9: Documentar setup inicial | E9: README.md | F9: FE-001, BE-001 | G9: Não iniciada | H9: README explica como subir frontend e backend | I9: Documentação | J9: Alta
A10: FE-004 | B10: 1 | C10: Frontend | D10: Criar layout global da aplicação | E10: frontend/src/app/layout.tsx; PageContainer.tsx | F10: FE-001 | G10: Não iniciada | H10: Layout global com regiões de sidebar, header e conteúdo | I10: Frontend | J10: Alta
A11: FE-005 | B11: 1 | C11: Frontend | D11: Implementar Sidebar | E11: frontend/src/components/layout/Sidebar.tsx | F11: FE-004 | G11: Não iniciada | H11: Sidebar funcional com navegação dos módulos | I11: Frontend | J11: Alta
A12: FE-006 | B12: 1 | C12: Frontend | D12: Implementar Header | E12: frontend/src/components/layout/Header.tsx | F12: FE-004 | G12: Não iniciada | H12: Header exibe nome da plataforma e título da página | I12: Frontend | J12: Alta
A13: FE-007 | B13: 1 | C13: Frontend | D13: Criar rotas-base dos módulos | E13: frontend/src/app/*/page.tsx para todos os módulos | F13: FE-005 | G13: Não iniciada | H13: Todas as páginas-base acessíveis via navegação | I13: Frontend | J13: Alta
... A151: DOC-011 | B151: 9 | C151: Documentação | D151: Documentar pós-MVP prioritário | E151: docs/api-contract.md; docs/user-guide.md; docs/architecture.md | F151: BE-059, FE-055 | G151: Não iniciada | H151: Pós-MVP prioritário documentado | I151: Documentação | J151: Média

Sheet Sprint_0
A1: ID | B1: Sprint | C1: Área | D1: Descrição | E1: Arquivos principais | F1: Dependências | G1: Status | H1: Critério de aceite | I1: Responsável principal | J1: Prioridade | K1: Data início | L1: Data conclusão | M1: Observações/Bloqueios
A2: OPS-001 | B2: 0 | C2: Operação | D2: Criar estrutura raiz do repositório | E2: .gitignore; .env.example; README.md; Makefile; diretórios base | F2: — | G2: Não iniciada | H2: Estrutura raiz criada e consistente com a arquitetura | I2: Arquiteto / DevOps | J2: Alta
A3: BE-001 | B3: 0 | C3: Backend | D3: Inicializar backend FastAPI | E3: backend/app/main.py; backend/app/api/; backend/app/core/; requirements/pyproject | F3: OPS-001 | G3: Não iniciada | H3: Backend sobe localmente | I3: Backend | J3: Alta
A4: BE-002 | B4: 0 | C4: Backend | D4: Implementar endpoint /health | E4: backend/app/api/routes/health.py; backend/app/main.py | F4: BE-001 | G4: Não iniciada | H4: GET /health responde 200 com payload mínimo | I4: Backend | J4: Alta
A5: FE-001 | B5: 0 | C5: Frontend | D5: Inicializar frontend Next.js com TypeScript | E5: frontend/package.json; tsconfig; src/app/layout.tsx; src/app/page.tsx | F5: OPS-001 | G5: Não iniciada | H5: Frontend sobe localmente | I5: Frontend | J5: Alta
A6: FE-002 | B6: 0 | C6: Frontend | D6: Criar cliente básico de API | E6: frontend/src/lib/api.ts; frontend/src/lib/constants.ts | F6: FE-001, BE-002 | G6: Não iniciada | H6: Frontend consegue chamar o backend | I6: Frontend | J6: Alta
A7: FE-003 | B7: 0 | C7: Frontend | D7: Criar página inicial técnica mínima | E7: frontend/src/app/page.tsx | F7: FE-002 | G7: Não iniciada | H7: Página inicial mostra status da API | I7: Frontend | J7: Média
A8: QA-001 | B8: 0 | C8: Testes | D8: Criar teste inicial do backend | E8: backend/tests/test_health.py | F8: BE-002 | G8: Não iniciada | H8: Teste cobre status 200 e contrato mínimo do /health | I8: QA / Backend | J8: Alta
A9: DOC-001 | B9: 0 | C9: Documentação | D9: Documentar setup inicial | E9: README.md | F9: FE-001, BE-001 | G9: Não iniciada | H9: README explica como subir frontend e backend | I9: Documentação | J9: Alta

Sheet Sprint_1
A1: ID | B1: Sprint | C1: Área | D1: Descrição | E1: Arquivos principais | F1: Dependências | G1: Status | H1: Critério de aceite | I1: Responsável principal | J1: Prioridade | K1: Data início | L1: Data conclusão | M1: Observações/Bloqueios
A2: FE-004 | B2: 1 | C2: Frontend | D2: Criar layout global da aplicação | E2: frontend/src/app/layout.tsx; PageContainer.tsx | F2: FE-001 | G2: Não iniciada | H2: Layout global com regiões de sidebar, header e conteúdo | I2: Frontend | J2: Alta
A3: FE-005 | B3: 1 | C3: Frontend | D3: Implementar Sidebar | E3: frontend/src/components/layout/Sidebar.tsx | F3: FE-004 | G3: Não iniciada | H3: Sidebar funcional com navegação dos módulos | I3: Frontend | J3: Alta
A4: FE-006 | B4: 1 | C4: Frontend | D4: Implementar Header | E4: frontend/src/components/layout/Header.tsx | F4: FE-004 | G4: Não iniciada | H4: Header exibe nome da plataforma e título da página | I4: Frontend | J4: Alta
A5: FE-007 | B5: 1 | C5: Frontend | D5: Criar rotas-base dos módulos | E5: frontend/src/app/*/page.tsx para todos os módulos | F5: FE-005 | G5: Não iniciada | H5: Todas as páginas-base acessíveis via navegação | I5: Frontend | J5: Alta
A6: FE-008 | B6: 1 | C6: Frontend | D6: Criar componentes de estado | E6: LoadingState.tsx; ErrorState.tsx; EmptyState.tsx | F6: FE-004 | G6: Não iniciada | H6: Estados reutilizáveis implementados | I6: Frontend | J6: Média
A7: FE-009 | B7: 1 | C7: Frontend | D7: Criar componentes-base reutilizáveis | E7: SummaryCard.tsx; AlertBanner.tsx; FormSection.tsx; EducationPanel.tsx | F7: FE-004 | G7: Não iniciada | H7: Componentes-base disponíveis e reutilizáveis | I7: Frontend | J7: Alta
A8: BE-003 | B8: 1 | C8: Backend | D8: Padronizar contrato-base de resposta | E8: response_models.py; exceptions.py | F8: BE-001 | G8: Não iniciada | H8: Sucesso e erro seguem padrão único | I8: Backend | J8: Alta
A9: BE-004 | B9: 1 | C9: Backend | D9: Padronizar tratamento inicial de erro | E9: exception_handlers.py | F9: BE-003 | G9: Não iniciada | H9: Validação e erro interno retornam contrato padronizado | I9: Backend | J9: Alta
A10: QA-002 | B10: 1 | C10: Testes | D10: Testar contrato-base do backend | E10: backend/tests/test_response_contract.py | F10: BE-003, BE-004 | G10: Não iniciada | H10: Contrato-base de sucesso e erro protegido por testes | I10: QA / Backend | J10: Alta
A11: DOC-002 | B11: 1 | C11: Documentação | D11: Atualizar documentação da arquitetura inicial | E11: docs/architecture.md; README.md | F11: FE-007, BE-003 | G11: Não iniciada | H11: Arquitetura inicial e padrão de resposta documentados | I11: Documentação | J11: Média

Sheet Sprint_2
A1: ID | B1: Sprint | C1: Área | D1: Descrição | E1: Arquivos principais | F1: Dependências | G1: Status | H1: Critério de aceite | I1: Responsável principal | J1: Prioridade | K1: Data início | L1: Data conclusão | M1: Observações/Bloqueios
A2: BE-005 | B2: 2 | C2: Backend | D2: Criar schemas do módulo de juros | E2: backend/app/schemas/interest.py | F2: BE-003 | G2: Não iniciada | H2: Payload de entrada e saída formalizados | I2: Backend | J2: Alta
A3: BE-006 | B3: 2 | C3: Backend | D3: Implementar domínio de juros simples | E3: backend/app/domain/interest/simple_interest.py | F3: BE-005 | G3: Não iniciada | H3: Função pura calcula montante e tabela temporal corretamente | I3: Backend | J3: Alta
A4: BE-007 | B4: 2 | C4: Backend | D4: Implementar domínio de juros compostos | E4: backend/app/domain/interest/compound_interest.py | F4: BE-005 | G4: Não iniciada | H4: Função pura calcula capitalização e tabela temporal corretamente | I4: Backend | J4: Alta
A5: BE-008 | B5: 2 | C5: Backend | D5: Implementar serviço comparativo de juros | E5: backend/app/services/interest_service.py | F5: BE-006, BE-007 | G5: Não iniciada | H5: Serviço monta summary, tables, charts, interpretation, alerts | I5: Backend | J5: Alta
A6: BE-009 | B6: 2 | C6: Backend | D6: Criar endpoint do módulo de juros | E6: backend/app/api/routes/interest.py | F6: BE-008 | G6: Não iniciada | H6: POST /api/v1/interest/simple-compound funcional | I6: Backend | J6: Alta
A7: FE-010 | B7: 2 | C7: Frontend | D7: Criar página funcional do módulo de juros | E7: frontend/src/app/juros/page.tsx | F7: FE-007 | G7: Não iniciada | H7: Página do módulo estruturada e pronta para integração | I7: Frontend | J7: Alta
A8: FE-011 | B8: 2 | C8: Frontend | D8: Criar formulário do módulo de juros | E8: InterestForm.tsx | F8: FE-010 | G8: Não iniciada | H8: Formulário envia dados válidos para a API | I8: Frontend | J8: Alta
A9: FE-012 | B9: 2 | C9: Frontend | D9: Criar visualização do resultado de juros | E9: InterestSummaryCards.tsx; InterestEvolutionTable.tsx; InterestComparisonChart.tsx | F9: FE-011, BE-009 | G9: Não iniciada | H9: Cards, tabela, gráfico, alertas e interpretação renderizados | I9: Frontend | J9: Alta
A10: QA-003 | B10: 2 | C10: Testes | D10: Testes unitários do domínio de juros | E10: test_simple_interest.py; test_compound_interest.py | F10: BE-006, BE-007 | G10: Não iniciada | H10: Fórmulas protegidas por testes de domínio | I10: QA / Backend | J10: Alta
A11: QA-004 | B11: 2 | C11: Testes | D11: Teste de integração da rota de juros | E11: backend/tests/api/test_interest_route.py | F11: BE-009 | G11: Não iniciada | H11: Rota validada com contrato e estrutura corretos | I11: QA / Backend | J11: Alta
A12: QA-005 | B12: 2 | C12: Testes | D12: Testes básicos do frontend do módulo de juros | E12: juros/page.test.tsx; InterestForm.test.tsx | F12: FE-012 | G12: Não iniciada | H12: Formulário e exibição de resultado cobertos | I12: QA / Frontend | J12: Média
A13: DOC-003 | B13: 2 | C13: Documentação | D13: Documentar módulo de juros | E13: docs/api-contract.md; docs/formulas.md; docs/user-guide.md | F13: BE-009, FE-012 | G13: Não iniciada | H13: Endpoint, fórmula e uso documentados | I13: Documentação | J13: Média

Sheet Sprint_3
A1: ID | B1: Sprint | C1: Área | D1: Descrição | E1: Arquivos principais | F1: Dependências | G1: Status | H1: Critério de aceite | I1: Responsável principal | J1: Prioridade | K1: Data início | L1: Data conclusão | M1: Observações/Bloqueios
A2: BE-010 | B2: 3 | C2: Backend | D2: Criar schemas do módulo de amortização | E2: backend/app/schemas/amortization.py | F2: BE-003 | G2: Não iniciada | H2: Contratos de entrada e saída definidos | I2: Backend | J2: Alta
A3: BE-011 | B3: 3 | C3: Backend | D3: Implementar domínio Price | E3: backend/app/domain/amortization/price.py | F3: BE-010 | G3: Não iniciada | H3: Cálculo Price correto por período | I3: Backend | J3: Alta
A4: BE-012 | B4: 3 | C4: Backend | D4: Implementar domínio SAC | E4: backend/app/domain/amortization/sac.py | F4: BE-010 | G4: Não iniciada | H4: Cálculo SAC correto por período | I4: Backend | J4: Alta
A5: BE-013 | B5: 3 | C5: Backend | D5: Implementar serviço comparativo Price/SAC | E5: backend/app/services/amortization_service.py | F5: BE-011, BE-012 | G5: Não iniciada | H5: Serviço compara sistemas e estrutura resposta completa | I5: Backend | J5: Alta
A6: BE-014 | B6: 3 | C6: Backend | D6: Criar endpoint Price/SAC | E6: backend/app/api/routes/amortization.py | F6: BE-013 | G6: Não iniciada | H6: POST /api/v1/amortization/price-sac funcional | I6: Backend | J6: Alta
A7: FE-013 | B7: 3 | C7: Frontend | D7: Criar página funcional de amortização | E7: frontend/src/app/amortizacao/page.tsx | F7: FE-007 | G7: Não iniciada | H7: Página estruturada | I7: Frontend | J7: Alta
A8: FE-014 | B8: 3 | C8: Frontend | D8: Criar formulário de amortização | E8: AmortizationForm.tsx | F8: FE-013 | G8: Não iniciada | H8: Formulário envia valor, taxa e prazo corretamente | I8: Frontend | J8: Alta
A9: FE-015 | B9: 3 | C9: Frontend | D9: Criar visualização de amortização | E9: AmortizationSummaryCards.tsx; AmortizationTable.tsx; AmortizationBalanceChart.tsx | F9: FE-014, BE-014 | G9: Não iniciada | H9: Comparação, tabela, gráfico e interpretação visíveis | I9: Frontend | J9: Alta
A10: QA-006 | B10: 3 | C10: Testes | D10: Testes unitários Price e SAC | E10: test_price.py; test_sac.py | F10: BE-011, BE-012 | G10: Não iniciada | H10: Fórmulas e tabelas protegidas | I10: QA / Backend | J10: Alta
A11: QA-007 | B11: 3 | C11: Testes | D11: Teste de integração da rota de amortização | E11: backend/tests/api/test_amortization_route.py | F11: BE-014 | G11: Não iniciada | H11: Contrato e estrutura da rota validados | I11: QA / Backend | J11: Alta
A12: QA-008 | B12: 3 | C12: Testes | D12: Testes básicos do frontend de amortização | E12: frontend/src/app/amortizacao/page.test.tsx | F12: FE-015 | G12: Não iniciada | H12: Renderização e submissão do módulo cobertas | I12: QA / Frontend | J12: Média
A13: DOC-004 | B13: 3 | C13: Documentação | D13: Documentar amortização | E13: docs/formulas.md; docs/api-contract.md; docs/user-guide.md | F13: BE-014, FE-015 | G13: Não iniciada | H13: Fórmulas, endpoint e uso documentados | I13: Documentação | J13: Média

Sheet Sprint_4
A1: ID | B1: Sprint | C1: Área | D1: Descrição | E1: Arquivos principais | F1: Dependências | G1: Status | H1: Critério de aceite | I1: Responsável principal | J1: Prioridade | K1: Data início | L1: Data conclusão | M1: Observações/Bloqueios
A2: BE-015 | B2: 4 | C2: Backend | D2: Criar schemas do Diagnóstico | E2: backend/app/schemas/diagnostic.py | F2: BE-003 | G2: Não iniciada | H2: Contratos do diagnóstico definidos | I2: Backend | J2: Alta
A3: BE-016 | B3: 4 | C3: Backend | D3: Implementar domínio do Diagnóstico | E3: financial_health.py | F3: BE-015 | G3: Não iniciada | H3: Saldo, comprometimento, poupança e reserva calculados corretamente | I3: Backend | J3: Alta
A4: BE-017 | B4: 4 | C4: Backend | D4: Criar serviço do Diagnóstico | E4: diagnostic_service.py | F4: BE-016 | G4: Não iniciada | H4: Serviço monta resumo, alertas e interpretação | I4: Backend | J4: Alta
A5: BE-018 | B5: 4 | C5: Backend | D5: Criar endpoint do Diagnóstico | E5: backend/app/api/routes/diagnostic.py | F5: BE-017 | G5: Não iniciada | H5: POST /api/v1/diagnostic funcional | I5: Backend | J5: Alta
A6: FE-016 | B6: 4 | C6: Frontend | D6: Criar página do Diagnóstico | E6: frontend/src/app/diagnostico/page.tsx | F6: FE-007 | G6: Não iniciada | H6: Página do módulo criada | I6: Frontend | J6: Alta
A7: FE-017 | B7: 4 | C7: Frontend | D7: Criar formulário do Diagnóstico | E7: DiagnosticForm.tsx | F7: FE-016 | G7: Não iniciada | H7: Formulário envia renda, despesas e dívidas corretamente | I7: Frontend | J7: Alta
A8: FE-018 | B8: 4 | C8: Frontend | D8: Criar cards e visualização do Diagnóstico | E8: DiagnosticSummaryCards.tsx; IncomeExpenseChart.tsx | F8: FE-017, BE-018 | G8: Não iniciada | H8: Cards, gráfico e interpretação do diagnóstico exibidos | I8: Frontend | J8: Alta
A9: QA-009 | B9: 4 | C9: Testes | D9: Testes do Diagnóstico | E9: test_diagnostic.py; test_diagnostic_route.py | F9: BE-018 | G9: Não iniciada | H9: Regras e rota do diagnóstico protegidas | I9: QA / Backend | J9: Alta
A10: DOC-005 | B10: 4 | C10: Documentação | D10: Documentar Diagnóstico | E10: docs/user-guide.md | F10: BE-018, FE-018 | G10: Não iniciada | H10: Uso e interpretação do diagnóstico documentados | I10: Documentação | J10: Média
A11: BE-019 | B11: 4 | C11: Backend | D11: Criar schemas do Financiamento Imobiliário | E11: real_estate_financing.py | F11: BE-003 | G11: Não iniciada | H11: Contratos do módulo definidos | I11: Backend | J11: Alta
A12: BE-020 | B12: 4 | C12: Backend | D12: Implementar domínio do Financiamento Imobiliário | E12: backend/app/domain/financing/real_estate.py | F12: BE-019, BE-011, BE-012 | G12: Não iniciada | H12: Valor financiado, parcelas, total pago e juros calculados corretamente | I12: Backend | J12: Alta
A13: BE-021 | B13: 4 | C13: Backend | D13: Criar serviço do Financiamento Imobiliário | E13: real_estate_financing_service.py | F13: BE-020 | G13: Não iniciada | H13: Serviço monta comparação PRICE/SAC, alertas e interpretação | I13: Backend | J13: Alta
... A20: DOC-006 | B20: 4 | C20: Documentação | D20: Documentar Diagnóstico e Financiamento Imobiliário | E20: docs/api-contract.md; docs/user-guide.md | F20: BE-022, FE-021 | G20: Não iniciada | H20: Endpoints e uso dos módulos documentados | I20: Documentação | J20: Média

Sheet Sprint_5
A1: ID | B1: Sprint | C1: Área | D1: Descrição | E1: Arquivos principais | F1: Dependências | G1: Status | H1: Critério de aceite | I1: Responsável principal | J1: Prioridade | K1: Data início | L1: Data conclusão | M1: Observações/Bloqueios
A2: BE-023 | B2: 5 | C2: Backend | D2: Criar schema de Financiamento de Veículo | E2: vehicle_financing.py | F2: BE-003 | G2: Não iniciada | H2: Contrato do módulo definido | I2: Backend | J2: Alta
A3: BE-024 | B3: 5 | C3: Backend | D3: Implementar domínio de Financiamento de Veículo | E3: backend/app/domain/financing/vehicle.py | F3: BE-023 | G3: Não iniciada | H3: Parcela, total pago, juros e comprometimento calculados corretamente | I3: Backend | J3: Alta
A4: BE-025 | B4: 5 | C4: Backend | D4: Criar serviço de Financiamento de Veículo | E4: vehicle_financing_service.py | F4: BE-024 | G4: Não iniciada | H4: Serviço monta resumo, alertas e interpretação | I4: Backend | J4: Alta
A5: BE-026 | B5: 5 | C5: Backend | D5: Criar endpoint de Financiamento de Veículo | E5: vehicle_financing.py route | F5: BE-025 | G5: Não iniciada | H5: POST /api/v1/financing/vehicle funcional | I5: Backend | J5: Alta
A6: FE-022 | B6: 5 | C6: Frontend | D6: Criar página do Financiamento de Veículo | E6: frontend/src/app/financiamento-veiculo/page.tsx | F6: FE-007 | G6: Não iniciada | H6: Página do módulo criada | I6: Frontend | J6: Alta
A7: FE-023 | B7: 5 | C7: Frontend | D7: Criar formulário do Financiamento de Veículo | E7: VehicleFinancingForm.tsx | F7: FE-022 | G7: Não iniciada | H7: Formulário funcional | I7: Frontend | J7: Alta
A8: FE-024 | B8: 5 | C8: Frontend | D8: Criar cards/tabela/gráfico do Financiamento de Veículo | E8: componentes do módulo | F8: FE-023, BE-026 | G8: Não iniciada | H8: Resultado do módulo exibido com clareza | I8: Frontend | J8: Alta
A9: BE-027 | B9: 5 | C9: Backend | D9: Criar schema do Consignado | E9: payroll_loan.py | F9: BE-003 | G9: Não iniciada | H9: Contrato do módulo definido | I9: Backend | J9: Alta
A10: BE-028 | B10: 5 | C10: Backend | D10: Implementar domínio do Consignado | E10: backend/app/domain/loans/payroll.py | F10: BE-027 | G10: Não iniciada | H10: Parcela, total pago e margem consignável calculados corretamente | I10: Backend | J10: Alta
A11: BE-029 | B11: 5 | C11: Backend | D11: Criar serviço do Consignado | E11: payroll_loan_service.py | F11: BE-028 | G11: Não iniciada | H11: Serviço monta alerta de margem e interpretação | I11: Backend | J11: Alta
A12: BE-030 | B12: 5 | C12: Backend | D12: Criar endpoint do Consignado | E12: backend/app/api/routes/payroll_loan.py | F12: BE-029 | G12: Não iniciada | H12: POST /api/v1/loan/payroll funcional | I12: Backend | J12: Alta
A13: FE-025 | B13: 5 | C13: Frontend | D13: Criar página do Consignado | E13: frontend/src/app/emprestimo-consignado/page.tsx | F13: FE-007 | G13: Não iniciada | H13: Página criada | I13: Frontend | J13: Alta
... A25: DOC-007 | B25: 5 | C25: Documentação | D25: Documentar os três módulos | E25: docs/api-contract.md; docs/user-guide.md | F25: BE-034, FE-030 | G25: Não iniciada | H25: Uso e endpoints documentados | I25: Documentação | J25: Média

Sheet Sprint_6
A1: ID | B1: Sprint | C1: Área | D1: Descrição | E1: Arquivos principais | F1: Dependências | G1: Status | H1: Critério de aceite | I1: Responsável principal | J1: Prioridade | K1: Data início | L1: Data conclusão | M1: Observações/Bloqueios
A2: BE-035 | B2: 6 | C2: Backend | D2: Criar schema do Rotativo | E2: revolving_credit.py | F2: BE-003 | G2: Não iniciada | H2: Contrato do módulo definido | I2: Backend | J2: Alta
A3: BE-036 | B3: 6 | C3: Backend | D3: Implementar domínio do Rotativo | E3: backend/app/domain/credit_card/revolving.py | F3: BE-035 | G3: Não iniciada | H3: Saldo remanescente e projeções calculados corretamente | I3: Backend | J3: Alta
A4: BE-037 | B4: 6 | C4: Backend | D4: Criar serviço do Rotativo | E4: revolving_credit_service.py | F4: BE-036 | G4: Não iniciada | H4: Serviço monta cenários comparativos e alertas | I4: Backend | J4: Alta
A5: BE-038 | B5: 6 | C5: Backend | D5: Criar endpoint do Rotativo | E5: backend/app/api/routes/revolving_credit.py | F5: BE-037 | G5: Não iniciada | H5: POST /api/v1/credit-card/revolving funcional | I5: Backend | J5: Alta
A6: FE-031 | B6: 6 | C6: Frontend | D6: Criar página do Rotativo | E6: frontend/src/app/cartao-rotativo/page.tsx | F6: FE-007 | G6: Não iniciada | H6: Página criada | I6: Frontend | J6: Alta
A7: FE-032 | B7: 6 | C7: Frontend | D7: Criar formulário do Rotativo | E7: RevolvingCreditForm.tsx | F7: FE-031 | G7: Não iniciada | H7: Formulário funcional | I7: Frontend | J7: Alta
A8: FE-033 | B8: 6 | C8: Frontend | D8: Criar visualização do Rotativo | E8: componentes do módulo | F8: FE-032, BE-038 | G8: Não iniciada | H8: Cenários e alertas exibidos | I8: Frontend | J8: Alta
A9: BE-039 | B9: 6 | C9: Backend | D9: Criar schema de Parcela em Atraso | E9: late_payment.py | F9: BE-003 | G9: Não iniciada | H9: Contrato do módulo definido | I9: Backend | J9: Alta
A10: BE-040 | B10: 6 | C10: Backend | D10: Implementar domínio de Parcela em Atraso | E10: backend/app/domain/late_payment/calculator.py | F10: BE-039 | G10: Não iniciada | H10: Multa, mora, correção e memória calculadas corretamente | I10: Backend | J10: Alta
A11: BE-041 | B11: 6 | C11: Backend | D11: Criar serviço de Parcela em Atraso | E11: late_payment_service.py | F11: BE-040 | G11: Não iniciada | H11: Serviço gera tabela de atraso padrão e interpretação | I11: Backend | J11: Alta
A12: BE-042 | B12: 6 | C12: Backend | D12: Criar endpoint de Parcela em Atraso | E12: backend/app/api/routes/late_payment.py | F12: BE-041 | G12: Não iniciada | H12: POST /api/v1/late-payment funcional | I12: Backend | J12: Alta
A13: FE-034 | B13: 6 | C13: Frontend | D13: Criar página de Parcela em Atraso | E13: frontend/src/app/parcela-atraso/page.tsx | F13: FE-007 | G13: Não iniciada | H13: Página criada | I13: Frontend | J13: Alta
... A24: DOC-008 | B24: 6 | C24: Documentação | D24: Documentar rotativo, atraso e indicadores | E24: docs/api-contract.md; docs/user-guide.md; docs/formulas.md | F24: BE-045, FE-039 | G24: Não iniciada | H24: Conteúdo e contratos documentados | I24: Documentação | J24: Média

Sheet Sprint_7
A1: ID | B1: Sprint | C1: Área | D1: Descrição | E1: Arquivos principais | F1: Dependências | G1: Status | H1: Critério de aceite | I1: Responsável principal | J1: Prioridade | K1: Data início | L1: Data conclusão | M1: Observações/Bloqueios
A2: BE-046 | B2: 7 | C2: Backend | D2: Estruturar conteúdo educacional inicial | E2: contents.py; education_service.py; education.py | F2: BE-003 | G2: Não iniciada | H2: Conteúdos podem ser listados e recuperados | I2: Backend | J2: Média
A3: BE-047 | B3: 7 | C3: Backend | D3: Estruturar glossário inicial | E3: estruturas de glossário | F3: BE-046 | G3: Não iniciada | H3: Glossário disponível via API ou provider | I3: Backend | J3: Média
A4: BE-048 | B4: 7 | C4: Backend | D4: Estruturar FAQ inicial | E4: estruturas de FAQ | F4: BE-046 | G4: Não iniciada | H4: FAQ disponível via API ou provider | I4: Backend | J4: Média
A5: FE-040 | B5: 7 | C5: Frontend | D5: Criar página do Glossário | E5: frontend/src/app/glossario/page.tsx | F5: FE-007, BE-047 | G5: Não iniciada | H5: Glossário navegável | I5: Frontend | J5: Média
A6: FE-041 | B6: 7 | C6: Frontend | D6: Criar página de FAQ | E6: frontend/src/app/faq/page.tsx | F6: FE-007, BE-048 | G6: Não iniciada | H6: FAQ navegável | I6: Frontend | J6: Média
A7: FE-042 | B7: 7 | C7: Frontend | D7: Integrar EducationPanel aos módulos | E7: módulos do MVP + EducationPanel.tsx | F7: FE-009, BE-046 | G7: Não iniciada | H7: Módulos do MVP exibem bloco educativo contextual | I7: Frontend | J7: Alta
A8: FE-043 | B8: 7 | C8: Frontend | D8: Criar links contextuais para termos e FAQs | E8: componentes de ajuda contextual | F8: FE-040, FE-041, FE-042 | G8: Não iniciada | H8: Termos técnicos clicáveis ou acessíveis no contexto | I8: Frontend | J8: Média
A9: FE-044 | B9: 7 | C9: Frontend | D9: Revisar microcopy dos módulos do MVP | E9: páginas e componentes dos módulos do MVP | F9: FE-042 | G9: Não iniciada | H9: Linguagem consistente, clara e didática | I9: Frontend / Conteúdo | J9: Alta
A10: QA-016 | B10: 7 | C10: Testes | D10: Testes do conteúdo educacional | E10: testes de listagem, detalhe e renderização | F10: BE-048, FE-044 | G10: Não iniciada | H10: Conteúdo essencial acessível e coerente | I10: QA | J10: Média
A11: QA-017 | B11: 7 | C11: Testes | D11: Testes de navegação entre módulos e educação | E11: fluxos entre módulos, glossário e FAQ | F11: FE-043 | G11: Não iniciada | H11: Navegação contextual funcionando | I11: QA / Frontend | J11: Média
A12: DOC-009 | B12: 7 | C12: Documentação | D12: Documentar educação, glossário e FAQ | E12: docs/user-guide.md; docs/content-guide.md | F12: BE-048, FE-044 | G12: Não iniciada | H12: Camada educativa documentada | I12: Documentação | J12: Média

Sheet Sprint_8
A1: ID | B1: Sprint | C1: Área | D1: Descrição | E1: Arquivos principais | F1: Dependências | G1: Status | H1: Critério de aceite | I1: Responsável principal | J1: Prioridade | K1: Data início | L1: Data conclusão | M1: Observações/Bloqueios
A2: BE-049 | B2: 8 | C2: Backend | D2: Implementar serviço de exportação PDF | E2: pdf_exporter.py | F2: módulos do MVP concluídos | G2: Não iniciada | H2: PDF básico gerado com dados principais | I2: Backend | J2: Média
A3: BE-050 | B3: 8 | C3: Backend | D3: Implementar serviço de exportação Excel | E3: excel_exporter.py | F3: módulos do MVP concluídos | G3: Não iniciada | H3: Excel básico gerado com dados tabulares | I3: Backend | J3: Média
A4: BE-051 | B4: 8 | C4: Backend | D4: Criar rotas de exportação | E4: export_service.py; export.py | F4: BE-049, BE-050 | G4: Não iniciada | H4: Rotas de exportação funcionais | I4: Backend | J4: Média
A5: FE-045 | B5: 8 | C5: Frontend | D5: Criar botão de exportação reutilizável | E5: ExportButton.tsx | F5: FE-009, BE-051 | G5: Não iniciada | H5: Botão reutilizável integrado ao fluxo | I5: Frontend | J5: Média
A6: FE-046 | B6: 8 | C6: Frontend | D6: Integrar exportação aos módulos prioritários | E6: páginas dos módulos prioritários | F6: FE-045 | G6: Não iniciada | H6: Exportação acessível nos módulos prioritários | I6: Frontend | J6: Média
A7: FE-047 | B7: 8 | C7: Frontend | D7: Revisar responsividade global | E7: layout, páginas e componentes principais | F7: FE-046 | G7: Não iniciada | H7: Navegação e leitura adequadas em desktop/tablet/mobile | I7: Frontend | J7: Alta
A8: FE-048 | B8: 8 | C8: Frontend | D8: Revisar estados de erro e loading | E8: componentes e páginas do MVP | F8: FE-008, FE-047 | G8: Não iniciada | H8: Erros e carregamento consistentes em todo o MVP | I8: Frontend | J8: Alta
A9: FE-049 | B9: 8 | C9: Frontend | D9: Ajustes finais de consistência visual | E9: componentes-base e páginas do MVP | F9: FE-047, FE-048 | G9: Não iniciada | H9: Padrão visual uniforme | I9: Frontend / UX | J9: Alta
A10: QA-018 | B10: 8 | C10: Testes | D10: Testes de exportação | E10: backend e frontend de exportação | F10: BE-051, FE-046 | G10: Não iniciada | H10: PDF e Excel gerados e acionados corretamente | I10: QA | J10: Média
A11: QA-019 | B11: 8 | C11: Testes | D11: Regressão principal do backend | E11: suíte de regressão dos módulos do MVP | F11: todos os módulos do MVP | G11: Não iniciada | H11: Módulos centrais mantêm comportamento válido | I11: QA / Backend | J11: Alta
A12: QA-020 | B12: 8 | C12: Testes | D12: Regressão principal do frontend | E12: suíte de regressão do MVP | F12: todos os módulos do MVP | G12: Não iniciada | H12: Fluxos centrais permanecem íntegros | I12: QA / Frontend | J12: Alta
A13: QA-021 | B13: 8 | C13: Testes | D13: Checklist manual do MVP | E13: checklist operacional | F13: FE-049, QA-019, QA-020 | G13: Não iniciada | H13: MVP validado ponta a ponta manualmente | I13: QA / Produto | J13: Alta
A14: DOC-010 | B14: 8 | C14: Documentação | D14: Documentar exportação e fechamento do MVP | E14: README.md; docs/user-guide.md; docs/api-contract.md | F14: BE-051, FE-046 | G14: Não iniciada | H14: Execução, exportação e uso do MVP documentados | I14: Documentação | J14: Média

Sheet Sprint_9
A1: ID | B1: Sprint | C1: Área | D1: Descrição | E1: Arquivos principais | F1: Dependências | G1: Status | H1: Critério de aceite | I1: Responsável principal | J1: Prioridade | K1: Data início | L1: Data conclusão | M1: Observações/Bloqueios
A2: BE-052 | B2: 9 | C2: Backend | D2: Criar schema de Investir ou Quitar | E2: invest_vs_debt.py | F2: BE-003 | G2: Não iniciada | H2: Contrato do módulo definido | I2: Backend | J2: Média
A3: BE-053 | B3: 9 | C3: Backend | D3: Implementar domínio Investir ou Quitar | E3: backend/app/domain/invest_vs_debt/calculator.py | F3: BE-052 | G3: Não iniciada | H3: Cenários quitar, investir e híbrido calculados corretamente | I3: Backend | J3: Média
A4: BE-054 | B4: 9 | C4: Backend | D4: Criar serviço Investir ou Quitar | E4: invest_vs_debt_service.py | F4: BE-053 | G4: Não iniciada | H4: Serviço monta comparação, alertas e interpretação | I4: Backend | J4: Média
A5: BE-055 | B5: 9 | C5: Backend | D5: Criar endpoint Investir ou Quitar | E5: backend/app/api/routes/invest_vs_debt.py | F5: BE-054 | G5: Não iniciada | H5: POST /api/v1/invest-vs-debt funcional | I5: Backend | J5: Média
A6: FE-050 | B6: 9 | C6: Frontend | D6: Criar página Investir ou Quitar | E6: frontend/src/app/investir-ou-quitar/page.tsx | F6: FE-007 | G6: Não iniciada | H6: Página criada | I6: Frontend | J6: Média
A7: FE-051 | B7: 9 | C7: Frontend | D7: Criar formulário Investir ou Quitar | E7: InvestVsDebtForm.tsx | F7: FE-050 | G7: Não iniciada | H7: Formulário funcional | I7: Frontend | J7: Média
A8: FE-052 | B8: 9 | C8: Frontend | D8: Criar visualização comparativa Investir ou Quitar | E8: componentes do módulo | F8: FE-051, BE-055 | G8: Não iniciada | H8: Três cenários exibidos com interpretação | I8: Frontend | J8: Média
A9: BE-056 | B9: 9 | C9: Backend | D9: Criar modelos iniciais de persistência de simulação | E9: simulation.py; simulation_input.py; simulation_result.py | F9: Arquitetura base | G9: Não iniciada | H9: Modelos coerentes com a modelagem de dados | I9: Backend | J9: Média
A10: BE-057 | B10: 9 | C10: Backend | D10: Criar repositório de simulações | E10: simulation_repository.py | F10: BE-056 | G10: Não iniciada | H10: Persistência encapsulada em repositório | I10: Backend | J10: Média
A11: BE-058 | B11: 9 | C11: Backend | D11: Criar rotas básicas de histórico | E11: routes/simulations.py ou equivalente | F11: BE-057 | G11: Não iniciada | H11: Histórico inicial consultável | I11: Backend | J11: Média
A12: BE-059 | B12: 9 | C12: Backend | D12: Criar rotas básicas de cenário salvo | E12: rotas e serviço de cenários salvos | F12: BE-057 | G12: Não iniciada | H12: Cenários podem ser salvos e recuperados | I12: Backend | J12: Média
A13: FE-053 | B13: 9 | C13: Frontend | D13: Criar página ou seção de histórico | E13: página/área de histórico | F13: FE-007, BE-058 | G13: Não iniciada | H13: Histórico inicial navegável | I13: Frontend | J13: Média
... A19: DOC-011 | B19: 9 | C19: Documentação | D19: Documentar pós-MVP prioritário | E19: docs/api-contract.md; docs/user-guide.md; docs/architecture.md | F19: BE-059, FE-055 | G19: Não iniciada | H19: Pós-MVP prioritário documentado | I19: Documentação | J19: Média
